pyDataBank/__init__.py
pyDataBank/datafiles.py
pyDataBank/datapack.py
tests/__init__.py
tests/unit/__init__.py
tests/unit/test_datafiles.py
pyDataBank-0.2.dist-info/LICENSE
pyDataBank-0.2.dist-info/METADATA
pyDataBank-0.2.dist-info/WHEEL
pyDataBank-0.2.dist-info/top_level.txt
pyDataBank-0.2.dist-info/RECORD
