Metadata-Version: 2.1
Name: pyDataBank
Version: 0.2
Summary: module to manage a bunch of resource files using regex or dialogs
Home-page: https://github.com/20centcroak/pyDataBank
Author: 20centCroak
Author-email: 
License: UNKNOWN
Platform: UNKNOWN
Classifier: Programming Language :: Python :: 3
Classifier: License :: OSI Approved :: MIT License
Classifier: Operating System :: OS Independent
Requires-Python: >=3.6
